yellowbox/__init__.py
yellowbox/_pytest.py
yellowbox/_version.py
yellowbox/clients.py
yellowbox/containers.py
yellowbox/extras/__init__.py
yellowbox/extras/aerospike.py
yellowbox/extras/azure_storage.py
yellowbox/extras/fake_gcs.py
yellowbox/extras/http_server.py
yellowbox/extras/kafka.py
yellowbox/extras/logstash.py
yellowbox/extras/mssql.py
yellowbox/extras/postgresql.py
yellowbox/extras/rabbit_mq.py
yellowbox/extras/redis.py
yellowbox/extras/sql_base.py
yellowbox/extras/vault.py
yellowbox/extras/webserver/__init__.py
yellowbox/extras/webserver/class_endpoint.py
yellowbox/extras/webserver/endpoints.py
yellowbox/extras/webserver/http_request_capture.py
yellowbox/extras/webserver/request_capture.py
yellowbox/extras/webserver/util.py
yellowbox/extras/webserver/webserver.py
yellowbox/extras/webserver/ws_request_capture.py
yellowbox/extras/websocket.py
yellowbox/image_build.py
yellowbox/networks.py
yellowbox/py.typed
yellowbox/retry.py
yellowbox/service.py
yellowbox/subclasses.py
yellowbox/utils.py
yellowbox-0.11.2.dist-info/METADATA
yellowbox-0.11.2.dist-info/WHEEL
yellowbox-0.11.2.dist-info/entry_points.txt
yellowbox-0.11.2.dist-info/licenses/LICENSE
yellowbox-0.11.2.dist-info/RECORD
