Metadata-Version: 2.4
Name: yellowbox
Version: 0.11.2
Summary: 
License: MIT
License-File: LICENSE
Author: biocatch ltd
Requires-Python: >=3.10,<4.0
Classifier: License :: OSI Approved :: MIT License
Classifier: Programming Language :: Python :: 3
Classifier: Programming Language :: Python :: 3.10
Classifier: Programming Language :: Python :: 3.11
Classifier: Programming Language :: Python :: 3.12
Classifier: Programming Language :: Python :: 3.13
Classifier: Programming Language :: Python :: 3.14
Provides-Extra: aerospike
Provides-Extra: azure
Provides-Extra: dev
Provides-Extra: gcs
Provides-Extra: kafka
Provides-Extra: mssql
Provides-Extra: postgresql
Provides-Extra: rabbit
Provides-Extra: redis
Provides-Extra: vault
Provides-Extra: webserver
Provides-Extra: websocket
Requires-Dist: Deprecated (>=1.2.13)
Requires-Dist: SQLAlchemy-Utils (>=0.38.2) ; extra == "postgresql" or extra == "mssql" or extra == "dev"
Requires-Dist: aerospike (>=10.0.1) ; extra == "aerospike" or extra == "dev"
Requires-Dist: async-timeout (>=4.0.3) ; (python_version < "3.11") and (extra == "redis" or extra == "dev")
Requires-Dist: azure-storage-blob (>=12.0.0) ; extra == "azure" or extra == "dev"
Requires-Dist: cffi (>=1.14.0) ; extra == "azure" or extra == "dev"
Requires-Dist: confluent-kafka ; (python_version >= "3.12") and (extra == "kafka")
Requires-Dist: docker (>=4.2.0)
Requires-Dist: hvac ; extra == "vault" or extra == "dev"
Requires-Dist: kafka-python ; (python_version < "3.12") and (extra == "kafka" or extra == "dev")
Requires-Dist: pika ; extra == "rabbit" or extra == "dev"
Requires-Dist: psycopg[binary] (>=3.2.12,<4.0.0) ; extra == "postgresql" or extra == "dev"
Requires-Dist: pyodbc (>=4.0.32) ; (python_version >= "3.8") and (extra == "dev")
Requires-Dist: pyodbc (>=5.0.0) ; (python_version >= "3.12") and (extra == "dev")
Requires-Dist: redis (>=3.3.0) ; extra == "redis" or extra == "dev"
Requires-Dist: requests
Requires-Dist: simple_websocket_server ; extra == "websocket" or extra == "dev"
Requires-Dist: sqlalchemy (>=2.0.0) ; extra == "postgresql" or extra == "mssql" or extra == "dev"
Requires-Dist: starlette (>=0.30) ; (python_version >= "3.12") and (extra == "webserver" or extra == "dev")
Requires-Dist: starlette (>=0.9) ; (python_version >= "3.8") and (extra == "webserver" or extra == "dev")
Requires-Dist: uvicorn (>=0.13) ; (python_version >= "3.8") and (extra == "webserver" or extra == "dev")
Requires-Dist: uvicorn (>=0.24) ; (python_version >= "3.12") and (extra == "webserver" or extra == "dev")
Requires-Dist: websockets ; extra == "webserver" or extra == "dev"
Requires-Dist: yaspin (>=1.0.0)
Project-URL: Repository, https://github.com/biocatchltd/yellowbox
